{
  "settings":{
    "exitPage":"./views/exitpage-sample.php",
    "exitFallback":"This page is in maintenance mode.",
    "dfltlogconsrvtn": 366,
    "minlogconsrvtn": 7,
    "recipientEmailAddress":"",
    "senderEmailAddress":""
  },
  "anomalies": {
    "1": {
      "logPath": "./test/logs/security-alerts.json",
      "daysBeforeExpiration": 366,
      "sendEmail": true
    },
    "2": {
      "logPath": "./test/logs/breaking-bugs.json",
      "daysBeforeExpiration": 183,
      "sendEmail": false
    },
    "3": {
      "logPath": "./test/logs/fails.json",
      "daysBeforeExpiration": 183,
      "sendEmail": false
    }
  }
}
